{"coordinates": null, "geo": null, "in_reply_to_status_id": null, "truncated": true, "lang": "en", "in_reply_to_status_id_str": null, "id_str": "942904686125965312", "is_quote_status": false, "contributors": null, "source": "<a href=\"https://studio.twitter.com\" rel=\"nofollow\">Media Studio</a>", "retweeted": false, "id": 942904686125965312, "possibly_sensitive": false, "entities": {"user_mentions": [], "symbols": [], "hashtags": [], "urls": [{"expanded_url": "https://twitter.com/i/web/status/942904686125965312", "display_url": "twitter.com/i/web/status/9\u2026", "indices": [117, 140], "url": "https://t.co/PCdvaFyy2D"}]}, "favorited": false, "favorite_count": 61062, "in_reply_to_user_id": null, "user": {"profile_banner_url": "https://pbs.twimg.com/profile_banners/25073877/1519516126", "profile_sidebar_fill_color": "C5CEC0", "default_profile_image": false, "has_extended_profile": false, "listed_count": 84381, "lang": "en", "translator_type": "regular", "statuses_count": 37022, "followers_count": 48317304, "time_zone": "Eastern Time (US & Canada)", "id_str": "25073877", "profile_background_image_url_https": "https://pbs.twimg.com/profile_background_images/530021613/trump_scotland__43_of_70_cc.jpg", "following": false, "profile_sidebar_border_color": "BDDCAD", "name": "Donald J. Trump", "profile_use_background_image": true, "utc_offset": -18000, "profile_background_color": "6D5C18", "profile_background_image_url": "http://pbs.twimg.com/profile_background_images/530021613/trump_scotland__43_of_70_cc.jpg", "verified": true, "default_profile": false, "notifications": false, "profile_image_url_https": "https://pbs.twimg.com/profile_images/874276197357596672/kUuht00m_normal.jpg", "location": "Washington, DC", "id": 25073877, "is_translation_enabled": true, "is_translator": false, "entities": {"description": {"urls": []}, "url": {"urls": [{"expanded_url": "http://www.Instagram.com/realDonaldTrump", "display_url": "Instagram.com/realDonaldTrump", "indices": [0, 23], "url": "https://t.co/OMxB0x7xC5"}]}}, "screen_name": "realDonaldTrump", "friends_count": 45, "favourites_count": 24, "protected": false, "description": "45th President of the United States of America\ud83c\uddfa\ud83c\uddf8", "url": "https://t.co/OMxB0x7xC5", "follow_request_sent": false, "profile_image_url": "http://pbs.twimg.com/profile_images/874276197357596672/kUuht00m_normal.jpg", "contributors_enabled": false, "geo_enabled": true, "profile_background_tile": true, "profile_link_color": "1B95E0", "created_at": "Wed Mar 18 13:46:38 +0000 2009", "profile_text_color": "333333"}, "in_reply_to_screen_name": null, "text": "With the strategy that I announced today, we are declaring that AMERICA is in the game and AMERICA is DETERMINED to\u2026 https://t.co/PCdvaFyy2D", "place": null, "retweet_count": 15628, "created_at": "Mon Dec 18 23:49:30 +0000 2017", "in_reply_to_user_id_str": null}
{"coordinates": null, "geo": null, "in_reply_to_status_id": null, "truncated": false, "lang": "en", "in_reply_to_status_id_str": null, "id_str": "942883507868782592", "is_quote_status": false, "contributors": null, "source": "<a href=\"http://twitter.com/download/iphone\" rel=\"nofollow\">Twitter for iPhone</a>", "retweeted": false, "id": 942883507868782592, "entities": {"user_mentions": [], "symbols": [], "hashtags": [], "urls": []}, "favorited": false, "favorite_count": 97627, "in_reply_to_user_id": null, "user": {"profile_banner_url": "https://pbs.twimg.com/profile_banners/25073877/1519516126", "profile_sidebar_fill_color": "C5CEC0", "default_profile_image": false, "has_extended_profile": false, "listed_count": 84381, "lang": "en", "translator_type": "regular", "statuses_count": 37022, "followers_count": 48317304, "time_zone": "Eastern Time (US & Canada)", "id_str": "25073877", "profile_background_image_url_https": "https://pbs.twimg.com/profile_background_images/530021613/trump_scotland__43_of_70_cc.jpg", "following": false, "profile_sidebar_border_color": "BDDCAD", "name": "Donald J. Trump", "profile_use_background_image": true, "utc_offset": -18000, "profile_background_color": "6D5C18", "profile_background_image_url": "http://pbs.twimg.com/profile_background_images/530021613/trump_scotland__43_of_70_cc.jpg", "verified": true, "default_profile": false, "notifications": false, "profile_image_url_https": "https://pbs.twimg.com/profile_images/874276197357596672/kUuht00m_normal.jpg", "location": "Washington, DC", "id": 25073877, "is_translation_enabled": true, "is_translator": false, "entities": {"description": {"urls": []}, "url": {"urls": [{"expanded_url": "http://www.Instagram.com/realDonaldTrump", "display_url": "Instagram.com/realDonaldTrump", "indices": [0, 23], "url": "https://t.co/OMxB0x7xC5"}]}}, "screen_name": "realDonaldTrump", "friends_count": 45, "favourites_count": 24, "protected": false, "description": "45th President of the United States of America\ud83c\uddfa\ud83c\uddf8", "url": "https://t.co/OMxB0x7xC5", "follow_request_sent": false, "profile_image_url": "http://pbs.twimg.com/profile_images/874276197357596672/kUuht00m_normal.jpg", "contributors_enabled": false, "geo_enabled": true, "profile_background_tile": true, "profile_link_color": "1B95E0", "created_at": "Wed Mar 18 13:46:38 +0000 2009", "profile_text_color": "333333"}, "in_reply_to_screen_name": null, "text": "70 Record Closes for the Dow so far this year! We have NEVER had 70 Dow Records in a one year period. Wow!", "place": null, "retweet_count": 21489, "created_at": "Mon Dec 18 22:25:20 +0000 2017", "in_reply_to_user_id_str": null}
{"coordinates": null, "geo": null, "in_reply_to_status_id": null, "truncated": false, "lang": "en", "in_reply_to_status_id_str": null, "quoted_status": {"coordinates": null, "geo": null, "in_reply_to_status_id": null, "truncated": false, "lang": "en", "in_reply_to_status_id_str": null, "id_str": "942055050259632130", "is_quote_status": false, "contributors": null, "source": "<a href=\"http://twitter.com/download/iphone\" rel=\"nofollow\">Twitter for iPhone</a>", "retweeted": false, "id": 942055050259632130, "possibly_sensitive": false, "entities": {"user_mentions": [{"screen_name": "MariaBartiromo", "name": "Maria Bartiromo", "id": 208155240, "id_str": "208155240", "indices": [97, 112]}], "symbols": [], "hashtags": [], "urls": [{"expanded_url": "https://www.wsj.com/articles/dow-24000-and-the-trump-boom-1513294061", "display_url": "wsj.com/articles/dow-2\u2026", "indices": [115, 138], "url": "https://t.co/AjVma9F84N"}]}, "favorited": false, "favorite_count": 20305, "in_reply_to_user_id": null, "user": {"profile_banner_url": "https://pbs.twimg.com/profile_banners/818927131883356161/1501886832", "profile_sidebar_fill_color": "DDEEF6", "default_profile_image": false, "has_extended_profile": false, "listed_count": 6441, "lang": "en", "translator_type": "none", "statuses_count": 1907, "followers_count": 2711080, "time_zone": "Pacific Time (US & Canada)", "id_str": "818927131883356161", "profile_background_image_url_https": null, "following": false, "profile_sidebar_border_color": "C0DEED", "name": "Sarah Sanders", "profile_use_background_image": true, "utc_offset": -28800, "profile_background_color": "F5F8FA", "profile_background_image_url": null, "verified": true, "default_profile": true, "notifications": false, "profile_image_url_https": "https://pbs.twimg.com/profile_images/893600318025474048/CbCbznYp_normal.jpg", "location": "Washington, D.C.", "id": 818927131883356161, "is_translation_enabled": false, "is_translator": false, "entities": {"description": {"urls": [{"expanded_url": "http://wh.gov/privacy", "display_url": "wh.gov/privacy", "indices": [105, 128], "url": "https://t.co/eVVzoBb3Zr"}]}, "url": {"urls": [{"expanded_url": "http://www.WhiteHouse.gov", "display_url": "WhiteHouse.gov", "indices": [0, 23], "url": "https://t.co/wyOVgSLgBV"}]}}, "screen_name": "PressSec", "friends_count": 236, "favourites_count": 314, "protected": false, "description": "@WhiteHouse Press Secretary. Proudly representing @POTUS Trump's Administration. Tweets may be archived: https://t.co/eVVzoBb3Zr.", "url": "https://t.co/wyOVgSLgBV", "follow_request_sent": false, "profile_image_url": "http://pbs.twimg.com/profile_images/893600318025474048/CbCbznYp_normal.jpg", "contributors_enabled": false, "geo_enabled": false, "profile_background_tile": false, "profile_link_color": "1DA1F2", "created_at": "Tue Jan 10 21:06:57 +0000 2017", "profile_text_color": "333333"}, "in_reply_to_screen_name": null, "text": "Trump administration \"Year One has been nothing short of excellent from an economic standpoint\" -@MariaBartiromo  \nhttps://t.co/AjVma9F84N", "place": null, "retweet_count": 6428, "created_at": "Sat Dec 16 15:33:21 +0000 2017", "in_reply_to_user_id_str": null}, "is_quote_status": true, "contributors": null, "source": "<a href=\"http://twitter.com/download/iphone\" rel=\"nofollow\">Twitter for iPhone</a>", "quoted_status_id_str": "942055050259632130", "retweeted": false, "quoted_status_id": 942055050259632130, "id_str": "942882250089271297", "id": 942882250089271297, "possibly_sensitive": false, "entities": {"user_mentions": [], "symbols": [], "hashtags": [], "urls": [{"expanded_url": "https://twitter.com/presssec/status/942055050259632130", "display_url": "twitter.com/presssec/statu\u2026", "indices": [19, 42], "url": "https://t.co/v1UR63CqLK"}]}, "favorited": false, "favorite_count": 40102, "in_reply_to_user_id": null, "user": {"profile_banner_url": "https://pbs.twimg.com/profile_banners/25073877/1519516126", "profile_sidebar_fill_color": "C5CEC0", "default_profile_image": false, "has_extended_profile": false, "listed_count": 84381, "lang": "en", "translator_type": "regular", "statuses_count": 37022, "followers_count": 48317304, "time_zone": "Eastern Time (US & Canada)", "id_str": "25073877", "profile_background_image_url_https": "https://pbs.twimg.com/profile_background_images/530021613/trump_scotland__43_of_70_cc.jpg", "following": false, "profile_sidebar_border_color": "BDDCAD", "name": "Donald J. Trump", "profile_use_background_image": true, "utc_offset": -18000, "profile_background_color": "6D5C18", "profile_background_image_url": "http://pbs.twimg.com/profile_background_images/530021613/trump_scotland__43_of_70_cc.jpg", "verified": true, "default_profile": false, "notifications": false, "profile_image_url_https": "https://pbs.twimg.com/profile_images/874276197357596672/kUuht00m_normal.jpg", "location": "Washington, DC", "id": 25073877, "is_translation_enabled": true, "is_translator": false, "entities": {"description": {"urls": []}, "url": {"urls": [{"expanded_url": "http://www.Instagram.com/realDonaldTrump", "display_url": "Instagram.com/realDonaldTrump", "indices": [0, 23], "url": "https://t.co/OMxB0x7xC5"}]}}, "screen_name": "realDonaldTrump", "friends_count": 45, "favourites_count": 24, "protected": false, "description": "45th President of the United States of America\ud83c\uddfa\ud83c\uddf8", "url": "https://t.co/OMxB0x7xC5", "follow_request_sent": false, "profile_image_url": "http://pbs.twimg.com/profile_images/874276197357596672/kUuht00m_normal.jpg", "contributors_enabled": false, "geo_enabled": true, "profile_background_tile": true, "profile_link_color": "1B95E0", "created_at": "Wed Mar 18 13:46:38 +0000 2009", "profile_text_color": "333333"}, "in_reply_to_screen_name": null, "text": "Thank you Maria B! https://t.co/v1UR63CqLK", "place": null, "retweet_count": 8651, "created_at": "Mon Dec 18 22:20:20 +0000 2017", "in_reply_to_user_id_str": null}
{"coordinates": null, "geo": null, "in_reply_to_status_id": null, "truncated": false, "lang": "en", "in_reply_to_status_id_str": null, "quoted_status": {"coordinates": null, "geo": null, "in_reply_to_status_id": null, "truncated": true, "lang": "en", "in_reply_to_status_id_str": null, "id_str": "942171573108314112", "is_quote_status": false, "contributors": null, "source": "<a href=\"http://twitter.com/download/iphone\" rel=\"nofollow\">Twitter for iPhone</a>", "retweeted": false, "id": 942171573108314112, "entities": {"user_mentions": [{"screen_name": "realDonaldTrump", "name": "Donald J. Trump", "id": 25073877, "id_str": "25073877", "indices": [83, 99]}], "symbols": [], "hashtags": [], "urls": [{"expanded_url": "https://twitter.com/i/web/status/942171573108314112", "display_url": "twitter.com/i/web/status/9\u2026", "indices": [116, 139], "url": "https://t.co/bwpvRNcgJ0"}]}, "favorited": false, "favorite_count": 21817, "in_reply_to_user_id": null, "user": {"profile_banner_url": "https://pbs.twimg.com/profile_banners/52544275/1482433261", "profile_sidebar_fill_color": "DDEEF6", "default_profile_image": false, "has_extended_profile": true, "listed_count": 19575, "lang": "en", "translator_type": "none", "statuses_count": 14044, "followers_count": 5437482, "time_zone": "Quito", "id_str": "52544275", "profile_background_image_url_https": "https://pbs.twimg.com/profile_background_images/378800000082251296/88912727d6e8e405d4a23881edd60def.jpeg", "following": false, "profile_sidebar_border_color": "000000", "name": "Ivanka Trump", "profile_use_background_image": true, "utc_offset": -18000, "profile_background_color": "C0DEED", "profile_background_image_url": "http://pbs.twimg.com/profile_background_images/378800000082251296/88912727d6e8e405d4a23881edd60def.jpeg", "verified": true, "default_profile": false, "notifications": false, "profile_image_url_https": "https://pbs.twimg.com/profile_images/882351803441987585/HWNkH-EK_normal.jpg", "location": "Washington, DC", "id": 52544275, "is_translation_enabled": false, "is_translator": false, "entities": {"description": {"urls": []}}, "screen_name": "IvankaTrump", "friends_count": 1123, "favourites_count": 1201, "protected": false, "description": "Wife, mother, sister, daughter. Advisor to POTUS on job creation + economic empowerment, workforce development & entrepreneurship. Personal Pg. Views are my own", "url": null, "follow_request_sent": false, "profile_image_url": "http://pbs.twimg.com/profile_images/882351803441987585/HWNkH-EK_normal.jpg", "contributors_enabled": false, "geo_enabled": true, "profile_background_tile": true, "profile_link_color": "FF6872", "created_at": "Tue Jun 30 22:32:03 +0000 2009", "profile_text_color": "333333"}, "in_reply_to_screen_name": null, "text": "The entrepreneurial spirit that built the American economy is alive and well under @realDonaldTrump \u2018s leadership.\u2026 https://t.co/bwpvRNcgJ0", "place": null, "retweet_count": 4164, "created_at": "Sat Dec 16 23:16:22 +0000 2017", "in_reply_to_user_id_str": null}, "is_quote_status": true, "contributors": null, "source": "<a href=\"http://twitter.com/download/iphone\" rel=\"nofollow\">Twitter for iPhone</a>", "quoted_status_id_str": "942171573108314112", "retweeted": false, "quoted_status_id": 942171573108314112, "id_str": "942881716913438720", "id": 942881716913438720, "possibly_sensitive": false, "entities": {"user_mentions": [], "symbols": [], "hashtags": [], "urls": [{"expanded_url": "https://twitter.com/ivankatrump/status/942171573108314112", "display_url": "twitter.com/ivankatrump/st\u2026", "indices": [16, 39], "url": "https://t.co/BNGUJG69Ki"}]}, "favorited": false, "favorite_count": 43994, "in_reply_to_user_id": null, "user": {"profile_banner_url": "https://pbs.twimg.com/profile_banners/25073877/1519516126", "profile_sidebar_fill_color": "C5CEC0", "default_profile_image": false, "has_extended_profile": false, "listed_count": 84381, "lang": "en", "translator_type": "regular", "statuses_count": 37022, "followers_count": 48317304, "time_zone": "Eastern Time (US & Canada)", "id_str": "25073877", "profile_background_image_url_https": "https://pbs.twimg.com/profile_background_images/530021613/trump_scotland__43_of_70_cc.jpg", "following": false, "profile_sidebar_border_color": "BDDCAD", "name": "Donald J. Trump", "profile_use_background_image": true, "utc_offset": -18000, "profile_background_color": "6D5C18", "profile_background_image_url": "http://pbs.twimg.com/profile_background_images/530021613/trump_scotland__43_of_70_cc.jpg", "verified": true, "default_profile": false, "notifications": false, "profile_image_url_https": "https://pbs.twimg.com/profile_images/874276197357596672/kUuht00m_normal.jpg", "location": "Washington, DC", "id": 25073877, "is_translation_enabled": true, "is_translator": false, "entities": {"description": {"urls": []}, "url": {"urls": [{"expanded_url": "http://www.Instagram.com/realDonaldTrump", "display_url": "Instagram.com/realDonaldTrump", "indices": [0, 23], "url": "https://t.co/OMxB0x7xC5"}]}}, "screen_name": "realDonaldTrump", "friends_count": 45, "favourites_count": 24, "protected": false, "description": "45th President of the United States of America\ud83c\uddfa\ud83c\uddf8", "url": "https://t.co/OMxB0x7xC5", "follow_request_sent": false, "profile_image_url": "http://pbs.twimg.com/profile_images/874276197357596672/kUuht00m_normal.jpg", "contributors_enabled": false, "geo_enabled": true, "profile_background_tile": true, "profile_link_color": "1B95E0", "created_at": "Wed Mar 18 13:46:38 +0000 2009", "profile_text_color": "333333"}, "in_reply_to_screen_name": null, "text": "So true Ivanka! https://t.co/BNGUJG69Ki", "place": null, "retweet_count": 8752, "created_at": "Mon Dec 18 22:18:13 +0000 2017", "in_reply_to_user_id_str": null}
{"coordinates": null, "geo": null, "in_reply_to_status_id": null, "truncated": true, "lang": "en", "in_reply_to_status_id_str": null, "id_str": "942857031693799425", "is_quote_status": false, "contributors": null, "source": "<a href=\"http://twitter.com/download/iphone\" rel=\"nofollow\">Twitter for iPhone</a>", "retweeted": false, "id": 942857031693799425, "possibly_sensitive": false, "entities": {"user_mentions": [], "symbols": [], "hashtags": [], "urls": [{"expanded_url": "https://twitter.com/i/web/status/942857031693799425", "display_url": "twitter.com/i/web/status/9\u2026", "indices": [117, 140], "url": "https://t.co/95522wIKVN"}]}, "favorited": false, "favorite_count": 48536, "in_reply_to_user_id": null, "user": {"profile_banner_url": "https://pbs.twimg.com/profile_banners/25073877/1519516126", "profile_sidebar_fill_color": "C5CEC0", "default_profile_image": false, "has_extended_profile": false, "listed_count": 84381, "lang": "en", "translator_type": "regular", "statuses_count": 37022, "followers_count": 48317304, "time_zone": "Eastern Time (US & Canada)", "id_str": "25073877", "profile_background_image_url_https": "https://pbs.twimg.com/profile_background_images/530021613/trump_scotland__43_of_70_cc.jpg", "following": false, "profile_sidebar_border_color": "BDDCAD", "name": "Donald J. Trump", "profile_use_background_image": true, "utc_offset": -18000, "profile_background_color": "6D5C18", "profile_background_image_url": "http://pbs.twimg.com/profile_background_images/530021613/trump_scotland__43_of_70_cc.jpg", "verified": true, "default_profile": false, "notifications": false, "profile_image_url_https": "https://pbs.twimg.com/profile_images/874276197357596672/kUuht00m_normal.jpg", "location": "Washington, DC", "id": 25073877, "is_translation_enabled": true, "is_translator": false, "entities": {"description": {"urls": []}, "url": {"urls": [{"expanded_url": "http://www.Instagram.com/realDonaldTrump", "display_url": "Instagram.com/realDonaldTrump", "indices": [0, 23], "url": "https://t.co/OMxB0x7xC5"}]}}, "screen_name": "realDonaldTrump", "friends_count": 45, "favourites_count": 24, "protected": false, "description": "45th President of the United States of America\ud83c\uddfa\ud83c\uddf8", "url": "https://t.co/OMxB0x7xC5", "follow_request_sent": false, "profile_image_url": "http://pbs.twimg.com/profile_images/874276197357596672/kUuht00m_normal.jpg", "contributors_enabled": false, "geo_enabled": true, "profile_background_tile": true, "profile_link_color": "1B95E0", "created_at": "Wed Mar 18 13:46:38 +0000 2009", "profile_text_color": "333333"}, "in_reply_to_screen_name": null, "text": "As the world watches, we are days away from passing HISTORIC TAX CUTS for American families and businesses. It will\u2026 https://t.co/95522wIKVN", "place": null, "retweet_count": 10031, "created_at": "Mon Dec 18 20:40:08 +0000 2017", "in_reply_to_user_id_str": null}
{"coordinates": null, "geo": null, "in_reply_to_status_id": null, "truncated": true, "lang": "en", "in_reply_to_status_id_str": null, "id_str": "942854056162332677", "is_quote_status": false, "contributors": null, "source": "<a href=\"http://twitter.com/download/iphone\" rel=\"nofollow\">Twitter for iPhone</a>", "retweeted": false, "id": 942854056162332677, "possibly_sensitive": false, "entities": {"user_mentions": [], "symbols": [], "hashtags": [], "urls": [{"expanded_url": "https://twitter.com/i/web/status/942854056162332677", "display_url": "twitter.com/i/web/status/9\u2026", "indices": [117, 140], "url": "https://t.co/p8hGEg9j3v"}]}, "favorited": false, "favorite_count": 48582, "in_reply_to_user_id": null, "user": {"profile_banner_url": "https://pbs.twimg.com/profile_banners/25073877/1519516126", "profile_sidebar_fill_color": "C5CEC0", "default_profile_image": false, "has_extended_profile": false, "listed_count": 84381, "lang": "en", "translator_type": "regular", "statuses_count": 37022, "followers_count": 48317304, "time_zone": "Eastern Time (US & Canada)", "id_str": "25073877", "profile_background_image_url_https": "https://pbs.twimg.com/profile_background_images/530021613/trump_scotland__43_of_70_cc.jpg", "following": false, "profile_sidebar_border_color": "BDDCAD", "name": "Donald J. Trump", "profile_use_background_image": true, "utc_offset": -18000, "profile_background_color": "6D5C18", "profile_background_image_url": "http://pbs.twimg.com/profile_background_images/530021613/trump_scotland__43_of_70_cc.jpg", "verified": true, "default_profile": false, "notifications": false, "profile_image_url_https": "https://pbs.twimg.com/profile_images/874276197357596672/kUuht00m_normal.jpg", "location": "Washington, DC", "id": 25073877, "is_translation_enabled": true, "is_translator": false, "entities": {"description": {"urls": []}, "url": {"urls": [{"expanded_url": "http://www.Instagram.com/realDonaldTrump", "display_url": "Instagram.com/realDonaldTrump", "indices": [0, 23], "url": "https://t.co/OMxB0x7xC5"}]}}, "screen_name": "realDonaldTrump", "friends_count": 45, "favourites_count": 24, "protected": false, "description": "45th President of the United States of America\ud83c\uddfa\ud83c\uddf8", "url": "https://t.co/OMxB0x7xC5", "follow_request_sent": false, "profile_image_url": "http://pbs.twimg.com/profile_images/874276197357596672/kUuht00m_normal.jpg", "contributors_enabled": false, "geo_enabled": true, "profile_background_tile": true, "profile_link_color": "1B95E0", "created_at": "Wed Mar 18 13:46:38 +0000 2009", "profile_text_color": "333333"}, "in_reply_to_screen_name": null, "text": "When the American People speak, ALL OF US should listen. Just over one year ago, you spoke loud and clear. On Novem\u2026 https://t.co/p8hGEg9j3v", "place": null, "retweet_count": 10277, "created_at": "Mon Dec 18 20:28:19 +0000 2017", "in_reply_to_user_id_str": null}
{"coordinates": null, "geo": null, "in_reply_to_status_id": null, "truncated": true, "lang": "en", "in_reply_to_status_id_str": null, "id_str": "942851788461563906", "is_quote_status": false, "contributors": null, "source": "<a href=\"http://twitter.com/download/iphone\" rel=\"nofollow\">Twitter for iPhone</a>", "retweeted": false, "id": 942851788461563906, "possibly_sensitive": false, "entities": {"user_mentions": [], "symbols": [], "hashtags": [], "urls": [{"expanded_url": "https://twitter.com/i/web/status/942851788461563906", "display_url": "twitter.com/i/web/status/9\u2026", "indices": [117, 140], "url": "https://t.co/ZUveaJ7Hv2"}]}, "favorited": false, "favorite_count": 64103, "in_reply_to_user_id": null, "user": {"profile_banner_url": "https://pbs.twimg.com/profile_banners/25073877/1519516126", "profile_sidebar_fill_color": "C5CEC0", "default_profile_image": false, "has_extended_profile": false, "listed_count": 84381, "lang": "en", "translator_type": "regular", "statuses_count": 37022, "followers_count": 48317304, "time_zone": "Eastern Time (US & Canada)", "id_str": "25073877", "profile_background_image_url_https": "https://pbs.twimg.com/profile_background_images/530021613/trump_scotland__43_of_70_cc.jpg", "following": false, "profile_sidebar_border_color": "BDDCAD", "name": "Donald J. Trump", "profile_use_background_image": true, "utc_offset": -18000, "profile_background_color": "6D5C18", "profile_background_image_url": "http://pbs.twimg.com/profile_background_images/530021613/trump_scotland__43_of_70_cc.jpg", "verified": true, "default_profile": false, "notifications": false, "profile_image_url_https": "https://pbs.twimg.com/profile_images/874276197357596672/kUuht00m_normal.jpg", "location": "Washington, DC", "id": 25073877, "is_translation_enabled": true, "is_translator": false, "entities": {"description": {"urls": []}, "url": {"urls": [{"expanded_url": "http://www.Instagram.com/realDonaldTrump", "display_url": "Instagram.com/realDonaldTrump", "indices": [0, 23], "url": "https://t.co/OMxB0x7xC5"}]}}, "screen_name": "realDonaldTrump", "friends_count": 45, "favourites_count": 24, "protected": false, "description": "45th President of the United States of America\ud83c\uddfa\ud83c\uddf8", "url": "https://t.co/OMxB0x7xC5", "follow_request_sent": false, "profile_image_url": "http://pbs.twimg.com/profile_images/874276197357596672/kUuht00m_normal.jpg", "contributors_enabled": false, "geo_enabled": true, "profile_background_tile": true, "profile_link_color": "1B95E0", "created_at": "Wed Mar 18 13:46:38 +0000 2009", "profile_text_color": "333333"}, "in_reply_to_screen_name": null, "text": "Over the past 11 months, I have travelled tens of thousands of miles, to visit 13 countries. I have met with more t\u2026 https://t.co/ZUveaJ7Hv2", "place": null, "retweet_count": 12982, "created_at": "Mon Dec 18 20:19:18 +0000 2017", "in_reply_to_user_id_str": null}
{"coordinates": null, "geo": null, "in_reply_to_status_id": null, "truncated": true, "lang": "en", "in_reply_to_status_id_str": null, "id_str": "942840800853024770", "is_quote_status": false, "contributors": null, "source": "<a href=\"http://twitter.com/download/iphone\" rel=\"nofollow\">Twitter for iPhone</a>", "retweeted": false, "id": 942840800853024770, "possibly_sensitive": false, "entities": {"user_mentions": [], "symbols": [], "hashtags": [], "urls": [{"expanded_url": "https://twitter.com/i/web/status/942840800853024770", "display_url": "twitter.com/i/web/status/9\u2026", "indices": [117, 140], "url": "https://t.co/kPYFsuSKL7"}]}, "favorited": false, "favorite_count": 42877, "in_reply_to_user_id": null, "user": {"profile_banner_url": "https://pbs.twimg.com/profile_banners/25073877/1519516126", "profile_sidebar_fill_color": "C5CEC0", "default_profile_image": false, "has_extended_profile": false, "listed_count": 84381, "lang": "en", "translator_type": "regular", "statuses_count": 37022, "followers_count": 48317304, "time_zone": "Eastern Time (US & Canada)", "id_str": "25073877", "profile_background_image_url_https": "https://pbs.twimg.com/profile_background_images/530021613/trump_scotland__43_of_70_cc.jpg", "following": false, "profile_sidebar_border_color": "BDDCAD", "name": "Donald J. Trump", "profile_use_background_image": true, "utc_offset": -18000, "profile_background_color": "6D5C18", "profile_background_image_url": "http://pbs.twimg.com/profile_background_images/530021613/trump_scotland__43_of_70_cc.jpg", "verified": true, "default_profile": false, "notifications": false, "profile_image_url_https": "https://pbs.twimg.com/profile_images/874276197357596672/kUuht00m_normal.jpg", "location": "Washington, DC", "id": 25073877, "is_translation_enabled": true, "is_translator": false, "entities": {"description": {"urls": []}, "url": {"urls": [{"expanded_url": "http://www.Instagram.com/realDonaldTrump", "display_url": "Instagram.com/realDonaldTrump", "indices": [0, 23], "url": "https://t.co/OMxB0x7xC5"}]}}, "screen_name": "realDonaldTrump", "friends_count": 45, "favourites_count": 24, "protected": false, "description": "45th President of the United States of America\ud83c\uddfa\ud83c\uddf8", "url": "https://t.co/OMxB0x7xC5", "follow_request_sent": false, "profile_image_url": "http://pbs.twimg.com/profile_images/874276197357596672/kUuht00m_normal.jpg", "contributors_enabled": false, "geo_enabled": true, "profile_background_tile": true, "profile_link_color": "1B95E0", "created_at": "Wed Mar 18 13:46:38 +0000 2009", "profile_text_color": "333333"}, "in_reply_to_screen_name": null, "text": "Our deepest sympathies and most heartfelt prayers are with the victims of the train derailment in Washington State.\u2026 https://t.co/kPYFsuSKL7", "place": null, "retweet_count": 8742, "created_at": "Mon Dec 18 19:35:38 +0000 2017", "in_reply_to_user_id_str": null}
{"coordinates": null, "geo": null, "in_reply_to_status_id": null, "truncated": true, "lang": "en", "in_reply_to_status_id_str": null, "id_str": "942829676699021312", "is_quote_status": false, "contributors": null, "source": "<a href=\"http://twitter.com/download/iphone\" rel=\"nofollow\">Twitter for iPhone</a>", "retweeted": false, "id": 942829676699021312, "entities": {"user_mentions": [], "symbols": [], "hashtags": [], "urls": [{"expanded_url": "https://twitter.com/i/web/status/942829676699021312", "display_url": "twitter.com/i/web/status/9\u2026", "indices": [117, 140], "url": "https://t.co/kw24I2Jm9t"}]}, "favorited": false, "favorite_count": 83831, "in_reply_to_user_id": null, "user": {"profile_banner_url": "https://pbs.twimg.com/profile_banners/25073877/1519516126", "profile_sidebar_fill_color": "C5CEC0", "default_profile_image": false, "has_extended_profile": false, "listed_count": 84381, "lang": "en", "translator_type": "regular", "statuses_count": 37022, "followers_count": 48317304, "time_zone": "Eastern Time (US & Canada)", "id_str": "25073877", "profile_background_image_url_https": "https://pbs.twimg.com/profile_background_images/530021613/trump_scotland__43_of_70_cc.jpg", "following": false, "profile_sidebar_border_color": "BDDCAD", "name": "Donald J. Trump", "profile_use_background_image": true, "utc_offset": -18000, "profile_background_color": "6D5C18", "profile_background_image_url": "http://pbs.twimg.com/profile_background_images/530021613/trump_scotland__43_of_70_cc.jpg", "verified": true, "default_profile": false, "notifications": false, "profile_image_url_https": "https://pbs.twimg.com/profile_images/874276197357596672/kUuht00m_normal.jpg", "location": "Washington, DC", "id": 25073877, "is_translation_enabled": true, "is_translator": false, "entities": {"description": {"urls": []}, "url": {"urls": [{"expanded_url": "http://www.Instagram.com/realDonaldTrump", "display_url": "Instagram.com/realDonaldTrump", "indices": [0, 23], "url": "https://t.co/OMxB0x7xC5"}]}}, "screen_name": "realDonaldTrump", "friends_count": 45, "favourites_count": 24, "protected": false, "description": "45th President of the United States of America\ud83c\uddfa\ud83c\uddf8", "url": "https://t.co/OMxB0x7xC5", "follow_request_sent": false, "profile_image_url": "http://pbs.twimg.com/profile_images/874276197357596672/kUuht00m_normal.jpg", "contributors_enabled": false, "geo_enabled": true, "profile_background_tile": true, "profile_link_color": "1B95E0", "created_at": "Wed Mar 18 13:46:38 +0000 2009", "profile_text_color": "333333"}, "in_reply_to_screen_name": null, "text": "My thoughts and prayers are with everyone involved in the train accident in DuPont, Washington. Thank you to all of\u2026 https://t.co/kw24I2Jm9t", "place": null, "retweet_count": 15198, "created_at": "Mon Dec 18 18:51:26 +0000 2017", "in_reply_to_user_id_str": null}
{"coordinates": null, "geo": null, "in_reply_to_status_id": null, "truncated": true, "lang": "en", "in_reply_to_status_id_str": null, "id_str": "942827072824672262", "is_quote_status": false, "contributors": null, "source": "<a href=\"http://twitter.com/download/iphone\" rel=\"nofollow\">Twitter for iPhone</a>", "retweeted": false, "id": 942827072824672262, "entities": {"user_mentions": [], "symbols": [], "hashtags": [], "urls": [{"expanded_url": "https://twitter.com/i/web/status/942827072824672262", "display_url": "twitter.com/i/web/status/9\u2026", "indices": [117, 140], "url": "https://t.co/K1e1absbxG"}]}, "favorited": false, "favorite_count": 106142, "in_reply_to_user_id": null, "user": {"profile_banner_url": "https://pbs.twimg.com/profile_banners/25073877/1519516126", "profile_sidebar_fill_color": "C5CEC0", "default_profile_image": false, "has_extended_profile": false, "listed_count": 84381, "lang": "en", "translator_type": "regular", "statuses_count": 37022, "followers_count": 48317304, "time_zone": "Eastern Time (US & Canada)", "id_str": "25073877", "profile_background_image_url_https": "https://pbs.twimg.com/profile_background_images/530021613/trump_scotland__43_of_70_cc.jpg", "following": false, "profile_sidebar_border_color": "BDDCAD", "name": "Donald J. Trump", "profile_use_background_image": true, "utc_offset": -18000, "profile_background_color": "6D5C18", "profile_background_image_url": "http://pbs.twimg.com/profile_background_images/530021613/trump_scotland__43_of_70_cc.jpg", "verified": true, "default_profile": false, "notifications": false, "profile_image_url_https": "https://pbs.twimg.com/profile_images/874276197357596672/kUuht00m_normal.jpg", "location": "Washington, DC", "id": 25073877, "is_translation_enabled": true, "is_translator": false, "entities": {"description": {"urls": []}, "url": {"urls": [{"expanded_url": "http://www.Instagram.com/realDonaldTrump", "display_url": "Instagram.com/realDonaldTrump", "indices": [0, 23], "url": "https://t.co/OMxB0x7xC5"}]}}, "screen_name": "realDonaldTrump", "friends_count": 45, "favourites_count": 24, "protected": false, "description": "45th President of the United States of America\ud83c\uddfa\ud83c\uddf8", "url": "https://t.co/OMxB0x7xC5", "follow_request_sent": false, "profile_image_url": "http://pbs.twimg.com/profile_images/874276197357596672/kUuht00m_normal.jpg", "contributors_enabled": false, "geo_enabled": true, "profile_background_tile": true, "profile_link_color": "1B95E0", "created_at": "Wed Mar 18 13:46:38 +0000 2009", "profile_text_color": "333333"}, "in_reply_to_screen_name": null, "text": "The train accident that just occurred in DuPont, WA shows more than ever why our soon to be submitted infrastructur\u2026 https://t.co/K1e1absbxG", "place": null, "retweet_count": 23023, "created_at": "Mon Dec 18 18:41:05 +0000 2017", "in_reply_to_user_id_str": null}
{"coordinates": null, "geo": null, "in_reply_to_status_id": null, "truncated": false, "lang": "en", "in_reply_to_status_id_str": null, "id_str": "942721681130483712", "is_quote_status": false, "contributors": null, "source": "<a href=\"http://twitter.com/download/iphone\" rel=\"nofollow\">Twitter for iPhone</a>", "retweeted": false, "id": 942721681130483712, "entities": {"user_mentions": [{"screen_name": "foxandfriends", "name": "FOX & friends", "id": 15513604, "id_str": "15513604", "indices": [36, 50]}], "symbols": [], "hashtags": [], "urls": []}, "favorited": false, "favorite_count": 44096, "in_reply_to_user_id": null, "user": {"profile_banner_url": "https://pbs.twimg.com/profile_banners/25073877/1519516126", "profile_sidebar_fill_color": "C5CEC0", "default_profile_image": false, "has_extended_profile": false, "listed_count": 84381, "lang": "en", "translator_type": "regular", "statuses_count": 37022, "followers_count": 48317304, "time_zone": "Eastern Time (US & Canada)", "id_str": "25073877", "profile_background_image_url_https": "https://pbs.twimg.com/profile_background_images/530021613/trump_scotland__43_of_70_cc.jpg", "following": false, "profile_sidebar_border_color": "BDDCAD", "name": "Donald J. Trump", "profile_use_background_image": true, "utc_offset": -18000, "profile_background_color": "6D5C18", "profile_background_image_url": "http://pbs.twimg.com/profile_background_images/530021613/trump_scotland__43_of_70_cc.jpg", "verified": true, "default_profile": false, "notifications": false, "profile_image_url_https": "https://pbs.twimg.com/profile_images/874276197357596672/kUuht00m_normal.jpg", "location": "Washington, DC", "id": 25073877, "is_translation_enabled": true, "is_translator": false, "entities": {"description": {"urls": []}, "url": {"urls": [{"expanded_url": "http://www.Instagram.com/realDonaldTrump", "display_url": "Instagram.com/realDonaldTrump", "indices": [0, 23], "url": "https://t.co/OMxB0x7xC5"}]}}, "screen_name": "realDonaldTrump", "friends_count": 45, "favourites_count": 24, "protected": false, "description": "45th President of the United States of America\ud83c\uddfa\ud83c\uddf8", "url": "https://t.co/OMxB0x7xC5", "follow_request_sent": false, "profile_image_url": "http://pbs.twimg.com/profile_images/874276197357596672/kUuht00m_normal.jpg", "contributors_enabled": false, "geo_enabled": true, "profile_background_tile": true, "profile_link_color": "1B95E0", "created_at": "Wed Mar 18 13:46:38 +0000 2009", "profile_text_color": "333333"}, "in_reply_to_screen_name": null, "text": "Ivanka Trump will be interviewed on @foxandfriends.", "place": null, "retweet_count": 6253, "created_at": "Mon Dec 18 11:42:18 +0000 2017", "in_reply_to_user_id_str": null}
{"coordinates": null, "geo": null, "in_reply_to_status_id": null, "truncated": true, "lang": "en", "in_reply_to_status_id_str": null, "id_str": "942717030091943936", "is_quote_status": false, "contributors": null, "source": "<a href=\"http://twitter.com/download/iphone\" rel=\"nofollow\">Twitter for iPhone</a>", "retweeted": false, "id": 942717030091943936, "entities": {"user_mentions": [], "symbols": [], "hashtags": [], "urls": [{"expanded_url": "https://twitter.com/i/web/status/942717030091943936", "display_url": "twitter.com/i/web/status/9\u2026", "indices": [117, 140], "url": "https://t.co/AmcJkgOSRk"}]}, "favorited": false, "favorite_count": 87566, "in_reply_to_user_id": null, "user": {"profile_banner_url": "https://pbs.twimg.com/profile_banners/25073877/1519516126", "profile_sidebar_fill_color": "C5CEC0", "default_profile_image": false, "has_extended_profile": false, "listed_count": 84381, "lang": "en", "translator_type": "regular", "statuses_count": 37022, "followers_count": 48317304, "time_zone": "Eastern Time (US & Canada)", "id_str": "25073877", "profile_background_image_url_https": "https://pbs.twimg.com/profile_background_images/530021613/trump_scotland__43_of_70_cc.jpg", "following": false, "profile_sidebar_border_color": "BDDCAD", "name": "Donald J. Trump", "profile_use_background_image": true, "utc_offset": -18000, "profile_background_color": "6D5C18", "profile_background_image_url": "http://pbs.twimg.com/profile_background_images/530021613/trump_scotland__43_of_70_cc.jpg", "verified": true, "default_profile": false, "notifications": false, "profile_image_url_https": "https://pbs.twimg.com/profile_images/874276197357596672/kUuht00m_normal.jpg", "location": "Washington, DC", "id": 25073877, "is_translation_enabled": true, "is_translator": false, "entities": {"description": {"urls": []}, "url": {"urls": [{"expanded_url": "http://www.Instagram.com/realDonaldTrump", "display_url": "Instagram.com/realDonaldTrump", "indices": [0, 23], "url": "https://t.co/OMxB0x7xC5"}]}}, "screen_name": "realDonaldTrump", "friends_count": 45, "favourites_count": 24, "protected": false, "description": "45th President of the United States of America\ud83c\uddfa\ud83c\uddf8", "url": "https://t.co/OMxB0x7xC5", "follow_request_sent": false, "profile_image_url": "http://pbs.twimg.com/profile_images/874276197357596672/kUuht00m_normal.jpg", "contributors_enabled": false, "geo_enabled": true, "profile_background_tile": true, "profile_link_color": "1B95E0", "created_at": "Wed Mar 18 13:46:38 +0000 2009", "profile_text_color": "333333"}, "in_reply_to_screen_name": null, "text": "Remember, Republicans are 5-0 in Congressional Races this year. The media refuses to mention this. I said Gillespie\u2026 https://t.co/AmcJkgOSRk", "place": null, "retweet_count": 18856, "created_at": "Mon Dec 18 11:23:49 +0000 2017", "in_reply_to_user_id_str": null}
{"coordinates": null, "geo": null, "in_reply_to_status_id": null, "truncated": true, "lang": "en", "in_reply_to_status_id_str": null, "id_str": "942551516564639744", "is_quote_status": false, "contributors": null, "source": "<a href=\"http://twitter.com/download/iphone\" rel=\"nofollow\">Twitter for iPhone</a>", "retweeted": false, "id": 942551516564639744, "possibly_sensitive": false, "entities": {"user_mentions": [], "symbols": [], "hashtags": [{"indices": [49, 64], "text": "WrightBrothers"}], "urls": [{"expanded_url": "https://twitter.com/i/web/status/942551516564639744", "display_url": "twitter.com/i/web/status/9\u2026", "indices": [121, 144], "url": "https://t.co/QPzu1tZjLZ"}]}, "favorited": false, "favorite_count": 60660, "in_reply_to_user_id": null, "user": {"profile_banner_url": "https://pbs.twimg.com/profile_banners/25073877/1519516126", "profile_sidebar_fill_color": "C5CEC0", "default_profile_image": false, "has_extended_profile": false, "listed_count": 84381, "lang": "en", "translator_type": "regular", "statuses_count": 37022, "followers_count": 48317304, "time_zone": "Eastern Time (US & Canada)", "id_str": "25073877", "profile_background_image_url_https": "https://pbs.twimg.com/profile_background_images/530021613/trump_scotland__43_of_70_cc.jpg", "following": false, "profile_sidebar_border_color": "BDDCAD", "name": "Donald J. Trump", "profile_use_background_image": true, "utc_offset": -18000, "profile_background_color": "6D5C18", "profile_background_image_url": "http://pbs.twimg.com/profile_background_images/530021613/trump_scotland__43_of_70_cc.jpg", "verified": true, "default_profile": false, "notifications": false, "profile_image_url_https": "https://pbs.twimg.com/profile_images/874276197357596672/kUuht00m_normal.jpg", "location": "Washington, DC", "id": 25073877, "is_translation_enabled": true, "is_translator": false, "entities": {"description": {"urls": []}, "url": {"urls": [{"expanded_url": "http://www.Instagram.com/realDonaldTrump", "display_url": "Instagram.com/realDonaldTrump", "indices": [0, 23], "url": "https://t.co/OMxB0x7xC5"}]}}, "screen_name": "realDonaldTrump", "friends_count": 45, "favourites_count": 24, "protected": false, "description": "45th President of the United States of America\ud83c\uddfa\ud83c\uddf8", "url": "https://t.co/OMxB0x7xC5", "follow_request_sent": false, "profile_image_url": "http://pbs.twimg.com/profile_images/874276197357596672/kUuht00m_normal.jpg", "contributors_enabled": false, "geo_enabled": true, "profile_background_tile": true, "profile_link_color": "1B95E0", "created_at": "Wed Mar 18 13:46:38 +0000 2009", "profile_text_color": "333333"}, "in_reply_to_screen_name": null, "text": "More than a century after conquering flight, the #WrightBrothers continue to motivate &amp; inspire Americans, who neve\u2026 https://t.co/QPzu1tZjLZ", "place": null, "retweet_count": 13033, "created_at": "Mon Dec 18 00:26:07 +0000 2017", "in_reply_to_user_id_str": null}
